geosearch/__init__.py
geosearch/extract.py
geosearch/geosearch.py
geosearch-0.0.1.dist-info/DESCRIPTION.rst
geosearch-0.0.1.dist-info/METADATA
geosearch-0.0.1.dist-info/RECORD
geosearch-0.0.1.dist-info/WHEEL
geosearch-0.0.1.dist-info/metadata.json
geosearch-0.0.1.dist-info/top_level.txt
