Metadata-Version: 2.0
Name: geosearch
Version: 0.0.1
Summary: GeoSearch searchs and extracts country and city mentions from text
Home-page: https://github.com/shansixiong/geosearch
Author: Shawn Sixiong Shan
Author-email: shansixioing@uchicago.edu
License: MIT
Keywords: geosearch
Platform: UNKNOWN
